hello_gemini/__init__.py
hello_gemini/main.py
hello_gemini-0.2.0.dist-info/METADATA
hello_gemini-0.2.0.dist-info/WHEEL
hello_gemini-0.2.0.dist-info/entry_points.txt
hello_gemini-0.2.0.dist-info/top_level.txt
hello_gemini-0.2.0.dist-info/RECORD
