Metadata-Version: 2.1
Name: hello-gemini
Version: 0.2.0
